EduRPA/__init__.py
EduRPA/Document/DocumentAutomation.py
EduRPA/Document/__init__.py
EduRPA/Document/transform.py
edurpa_document-0.0.8.dist-info/LICENSE
edurpa_document-0.0.8.dist-info/METADATA
edurpa_document-0.0.8.dist-info/WHEEL
edurpa_document-0.0.8.dist-info/top_level.txt
edurpa_document-0.0.8.dist-info/RECORD
