Metadata-Version: 2.1
Name: edurpa-document
Version: 0.0.8
Summary: education librabry for RPA
Home-page: https://github.com/edu-rpa/edu-rpa-library
Author: david
Author-email: davidhuynh0222@gmail.com
Classifier: Programming Language :: Python :: 2
Classifier: License :: OSI Approved :: MIT License
Classifier: Operating System :: OS Independent
License-File: LICENSE
Requires-Dist: charset-normalizer (==3.3.2)
Requires-Dist: colorama (==0.4.6)
Requires-Dist: contourpy (==1.2.0)
Requires-Dist: cycler (==0.12.1)
Requires-Dist: einops (==0.2.0)
Requires-Dist: et-xmlfile (==1.1.0)
Requires-Dist: filelock (==3.13.1)
Requires-Dist: fonttools (==4.46.0)
Requires-Dist: gdown (==4.4.0)
Requires-Dist: idna (==3.6)
Requires-Dist: imageio (==2.33.0)
Requires-Dist: imgaug (==0.4.0)
Requires-Dist: importlib-resources (==6.1.1)
Requires-Dist: kiwisolver (==1.4.5)
Requires-Dist: lazy-loader (==0.3)
Requires-Dist: lmdb (==1.4.1)
Requires-Dist: matplotlib (==3.8.2)
Requires-Dist: networkx (==3.2.1)
Requires-Dist: numpy (==1.26.2)
Requires-Dist: opencv-python (==4.8.1.78)
Requires-Dist: openpyxl (==3.1.2)
Requires-Dist: packaging (==23.2)
Requires-Dist: prefetch-generator (==1.0.1)
Requires-Dist: pyparsing (==3.1.1)
Requires-Dist: PySocks (==1.7.1)
Requires-Dist: python-dateutil (==2.8.2)
Requires-Dist: requests (==2.31.0)
Requires-Dist: robotframework (==6.1.1)
Requires-Dist: scikit-image (==0.22.0)
Requires-Dist: scipy (==1.11.4)
Requires-Dist: shapely (==2.0.2)
Requires-Dist: six (==1.16.0)
Requires-Dist: soupsieve (==2.5)
Requires-Dist: tifffile (==2023.9.26)
Requires-Dist: tqdm (==4.66.1)
Requires-Dist: vietocr (==0.3.12)
Requires-Dist: zipp (==3.17.0)
Requires-Dist: editdistance
Requires-Dist: Pillow (==9.5.0)
